[
    { "code": "R-125", "name": "HFC-125", "gwp": 3500 },
    { "code": "R-134A", "name": "HFC-134a", "gwp": 1430 },
    { "code": "R-143A", "name": "HFC-143a", "gwp": 4470 },
    { "code": "R-152A", "name": "HFC-152a", "gwp": 124 },
    { "code": "R-22", "name": "HFC-22", "gwp": 1810 },
    { "code": "R-227EA", "name": "HFC-227EA", "gwp": 3220 },
    { "code": "R-23", "name": "HFC-23", "gwp": 14800 },
    { "code": "R-236CB", "name": "HFC-236CB", "gwp": 1340 },
    { "code": "R-236EA", "name": "HFC-236EA", "gwp": 1370 },
    { "code": "R-236FA", "name": "HFC-236FA", "gwp": 9810 },
    { "code": "R-245CA", "name": "HFC-245CA", "gwp": 693 },
    { "code": "R-245FA", "name": "HFC-245FA", "gwp": 1030 },
    { "code": "R-32", "name": "HFC-32", "gwp": 675 },
    { "code": "R-365MFC", "name": "HFC-365MFC", "gwp": 794 },
    { "code": "R-41", "name": "HFC-41", "gwp": 92 },
    { "code": "R-43-10MEE", "name": "HFC-43-10MEE", "gwp": 1640 },
    { "code": "R-404A", "name": "HFC-404A", "gwp": 3922 },
    { "code": "R-407A", "name": "HFC-407A", "gwp": 2107 },
    { "code": "R-407B", "name": "HFC-407B", "gwp": 2804 },
    { "code": "R-407C", "name": "HFC-407C", "gwp": 1774 },
    { "code": "R-407D", "name": "HFC-407D", "gwp": 1627 },
    { "code": "R-407E", "name": "HFC-407E", "gwp": 1552 },
    { "code": "R-407F", "name": "HFC-407F", "gwp": 1825 },
    { "code": "R-407G", "name": "HFC-407G", "gwp": 1463 },
    { "code": "R-410A", "name": "HFC-410A", "gwp": 2088 },
    { "code": "R-410B", "name": "HFC-410B", "gwp": 2229 },
    { "code": "R-413A", "name": "HFC-413A", "gwp": 2053 },
    { "code": "R-417A", "name": "HFC-417A", "gwp": 2346 },
    { "code": "R-417B", "name": "HFC-417B", "gwp": 3027 },
    { "code": "R-417C", "name": "HFC-417C", "gwp": 1809 },
    { "code": "R-419A", "name": "HFC-419A", "gwp": 2967 },
    { "code": "R-419B", "name": "HFC-419B", "gwp": 2384 },
    { "code": "R-421A", "name": "HFC-421A", "gwp": 2631 },
    { "code": "R-421B", "name": "HFC-421B", "gwp": 3190 },
    { "code": "R-422A", "name": "HFC-422A", "gwp": 3143 },
    { "code": "R-422B", "name": "HFC-422B", "gwp": 2526 },
    { "code": "R-422C", "name": "HFC-422C", "gwp": 3085 },
    { "code": "R-422D", "name": "HFC-422D", "gwp": 2729 },
    { "code": "R-422E", "name": "HFC-422E", "gwp": 2592 },
    { "code": "R-423A", "name": "HFC-423A", "gwp": 2280 },
    { "code": "R-424A", "name": "HFC-424A", "gwp": 2440 },
    { "code": "R-425A", "name": "HFC-425A", "gwp": 1505 },
    { "code": "R-426A", "name": "HFC-426A", "gwp": 1508 },
    { "code": "R-427A", "name": "HFC-427A", "gwp": 2138 },
    { "code": "R-428A", "name": "HFC-428A", "gwp": 3607 },
    { "code": "R-429A", "name": "HFC-429A", "gwp": 13 },
    { "code": "R-430A", "name": "HFC-430A", "gwp": 94 },
    { "code": "R-431A", "name": "HFC-431A", "gwp": 36 },
    { "code": "R-434A", "name": "HFC-434A", "gwp": 3245 },
    { "code": "R-435A", "name": "HFC-435A", "gwp": 26 },
    { "code": "R-437A", "name": "HFC-437A", "gwp": 1805 },
    { "code": "R-438A", "name": "HFC-438A", "gwp": 2264 },
    { "code": "R-439A", "name": "HFC-439A", "gwp": 1983 },
    { "code": "R-440A", "name": "HFC-440A", "gwp": 144 },
    { "code": "R-442A", "name": "HFC-442A", "gwp": 1888 },
    { "code": "R-444A", "name": "HFC-444A", "gwp": 87 },
    { "code": "R-444B", "name": "HFC-444B", "gwp": 293 },
    { "code": "R-445A", "name": "HFC-445A", "gwp": 129 },
    { "code": "R-446A", "name": "HFC-446A", "gwp": 459 },
    { "code": "R-447A", "name": "HFC-447A", "gwp": 582 },
    { "code": "R-447B", "name": "HFC-447B", "gwp": 739 },
    { "code": "R-448A", "name": "HFC-448A", "gwp": 1386 },
    { "code": "R-449A", "name": "HFC-449A", "gwp": 1396 },
    { "code": "R-449B", "name": "HFC-449B", "gwp": 1411 },
    { "code": "R-449C", "name": "HFC-449C", "gwp": 1250 },
    { "code": "R-450A", "name": "HFC-450A", "gwp": 601 },
    { "code": "R-451A", "name": "HFC-451A", "gwp": 146 },
    { "code": "R-451B", "name": "HFC-451B", "gwp": 160 },
    { "code": "R-452A", "name": "HFC-452A", "gwp": 2139 },
    { "code": "R-452B", "name": "HFC-452B", "gwp": 697 },
    { "code": "R-452C", "name": "HFC-452C", "gwp": 2219 },
    { "code": "R-453A", "name": "HFC-453A", "gwp": 1765 },
    { "code": "R-454A", "name": "HFC-454A", "gwp": 236 },
    { "code": "R-454B", "name": "HFC-454B", "gwp": 465 },
    { "code": "R-454C", "name": "HFC-454C", "gwp": 145 },
    { "code": "R-455A", "name": "HFC-455A", "gwp": 145 },
    { "code": "R-456A", "name": "HFC-456A", "gwp": 684 },
    { "code": "R-457A", "name": "HFC-457A", "gwp": 136 },
    { "code": "R-458A", "name": "HFC-458A", "gwp": 1650 },
    { "code": "R-500", "name": "HFC-500", "gwp": 8077 },
    { "code": "R-503", "name": "HFC-503", "gwp": 14560 },
    { "code": "R-507A", "name": "HFC-507A", "gwp": 3985 },
    { "code": "R-508A", "name": "HFC-508A", "gwp": 13214 },
    { "code": "R-508B", "name": "HFC-508B", "gwp": 13396 },
    { "code": "R-512A", "name": "HFC-512A", "gwp": 189 },
    { "code": "R-513A", "name": "HFC-513A", "gwp": 629 },
    { "code": "R-513B", "name": "HFC-513B", "gwp": 593 },
    { "code": "R-515A", "name": "HFC-515A", "gwp": 386 }
]
